pdcom5/LoginManager.py
pdcom5/Process.py
pdcom5/Subscription.py
pdcom5/Variable.py
pdcom5/_PdComWrapper.cpython-313-arm-linux-gnueabihf.so
pdcom5/__init__.py
pdcom5.libs/libcrypt-1baa4179.so.2.0.0
pdcom5.libs/libcrypto-894f4c86.so.3
pdcom5.libs/libpdcom5-59dcefa6.so.2.3.2
pdcom5.libs/libpdcom5-sasl-0e9e0846.so.2.3.2
pdcom5-5.3.2.dist-info/METADATA
pdcom5-5.3.2.dist-info/WHEEL
pdcom5-5.3.2.dist-info/top_level.txt
pdcom5-5.3.2.dist-info/RECORD
