Metadata-Version: 2.1
Name: pdcom5
Version: 5.3.2
Summary: Library for process data exchange
Home-page: https://etherlab.org
Author: Bjarne von Horn
Author-email: Bjarne von Horn <vh@igh.de>, Florian Pose <fp@igh.de>, Richard Hacker <ha@igh.de>
Project-URL: Homepage, https://gitlab.com/etherlab.org/pdcom
Project-URL: Bug Tracker, https://gitlab.com/etherlab.org/pdcom/-/issues
Classifier: Programming Language :: Python :: 3
Classifier: Development Status :: 4 - Beta
Classifier: License :: OSI Approved :: GNU Lesser General Public License v3 or later (LGPLv3+)
Requires-Python: >=3.6
Requires-Dist: numpy
